[
    {
        "title": "noon east Electric Stainless Steel Kettle With Power Indicator Light And Boil Dry Protection 1.5 L 1800 W KESS4008_WH White",
        "discount": "78% Off",
        "old_price": "AED 119",
        "new_price": "AED 25.00",
        "link": "noon.com/uae-en/electric-stainless-steel-kettle-with-power-indicator-light-and-boil-dry-protection-1-5-l-1800-w-kess4008-wh-white/N31981366A/p/?o=fb15c60466482c6c"
    },
    {
        "title": "noon east 12-Piece LR6 AA Alkaline Battery Set Yellow/Black 17.5 x 5.4 x 1.6cm",
        "discount": "75% Off",
        "old_price": "AED 49",
        "new_price": "AED 12.00",
        "link": "noon.com/uae-en/12-piece-lr6-aa-alkaline-battery-set-yellow-black-17-5-x-5-4-x-1-6cm/N39753573A/p/?o=dacb78845a10c65b"
    },
    {
        "title": "SUNSHINE Set Of 4 Anti Vibration Washing Machine Pads Multicolour 10.5cm",
        "discount": "75% Off",
        "old_price": "AED 60",
        "new_price": "AED 14.80",
        "link": "noon.com/uae-en/set-of-4-anti-vibration-washing-machine-pads-multicolour-10-5cm/N48441705A/p/?o=da79527e8175919d"
    },
    {
        "title": "Amal Carbon Steel Baking Pans Dark Grey Round 3-Piece Set",
        "discount": "79% Off",
        "old_price": "AED 69",
        "new_price": "AED 14.00",
        "link": "noon.com/uae-en/carbon-steel-baking-pans-dark-grey-round-3-piece-set/N39007180A/p/?o=d3c1114900ddfc8d"
    },
    {
        "title": "noon east 4-Piece LR6 AA Alkaline Battery Set Yellow/Black 11.5 x 8.5 x 2cm",
        "discount": "82% Off",
        "old_price": "AED 29",
        "new_price": "AED 5.00",
        "link": "noon.com/uae-en/4-piece-lr6-aa-alkaline-battery-set-yellow-black-11-5-x-8-5-x-2cm/N39753572A/p/?o=e1ba3474d181eece"
    },
    {
        "title": "Royalford Eco-friendly Reusable Double Wall Leakproof Coffee Travel Mug With Handle And Compact Lid Assorted 420ml",
        "discount": "89% Off",
        "old_price": "AED 99",
        "new_price": "AED 10.60",
        "link": "noon.com/uae-en/eco-friendly-reusable-double-wall-leakproof-coffee-travel-mug-with-handle-and-compact-lid-assorted-420ml/N37544112A/p/?o=ecbc72cd1ff7891a"
    },
    {
        "title": "Hometown Decorative Trendy Lustrous Area Rugs Multicolor 50X80cm",
        "discount": "76% Off",
        "old_price": "AED 63",
        "new_price": "AED 15.00",
        "link": "noon.com/uae-en/decorative-trendy-lustrous-area-rugs-multicolor-50x80cm/N46441751A/p/?o=c42b63b1b3fe3a5b"
    },
    {
        "title": "noon east 12-Piece Porcelain Dinner Set, Plates, Dishes, Bowls, Serves 4 Mink",
        "discount": "76% Off",
        "old_price": "AED 129",
        "new_price": "AED 30.00",
        "link": "noon.com/uae-en/12-piece-porcelain-dinner-set-plates-dishes-bowls-serves-4-mink/N39407375A/p/?o=e8d9a80f544cca6a"
    },
    {
        "title": "DaDa Home Removable Wall Sticker Mirror Clear 60x40centimeter",
        "discount": "76% Off",
        "old_price": "AED 59",
        "new_price": "AED 14.00",
        "link": "noon.com/uae-en/removable-wall-sticker-mirror-clear-60x40centimeter/N12621399A/p/?o=b758cce0061935af"
    },
    {
        "title": "Amal 144 Thread Count Home Essential Fitted Sheet Set/3 - 90X190+25cm, 2 Pillow Case 50X75 cm Cotton Grey Single",
        "discount": "79% Off",
        "old_price": "AED 159",
        "new_price": "AED 32.00",
        "link": "noon.com/uae-en/144-thread-count-home-essential-fitted-sheet-set-3-90x190-25cm-2-pillow-case-50x75-cm-cotton-grey-single/N43682810A/p/?o=bca20b6df42a677b"
    },
    {
        "title": "SKY-TOUCH 200 Pcs Air Fryer Liner, Round Non-Stick Steamer Mat, Premium Parchment Paper for Baking, Oven, Air Fryer, Bamboo Steamer - 7 inches White Multicolour 7inch",
        "discount": "75% Off",
        "old_price": "AED 69",
        "new_price": "AED 17.00",
        "link": "noon.com/uae-en/200-pcs-air-fryer-liner-round-non-stick-steamer-mat-premium-parchment-paper-for-baking-oven-air-fryer-bamboo-steamer-7-inches-white-multicolour-7inch/N39846520A/p/?o=e7e8c34e398196bc"
    },
    {
        "title": "noon east 12-Piece LR03 AAA Alkaline Battery Set Yellow/Black 13 x 4.7 x 1.2cm",
        "discount": "75% Off",
        "old_price": "AED 49",
        "new_price": "AED 12.00",
        "link": "noon.com/uae-en/12-piece-lr03-aaa-alkaline-battery-set-yellow-black-13-x-4-7-x-1-2cm/N39753576A/p/?o=d0b817249fb391ac"
    },
    {
        "title": "noon east 12-Piece Porcelain Dinner Set, Plates, Dishes, Bowls, Serves 4 Poppy",
        "discount": "76% Off",
        "old_price": "AED 129",
        "new_price": "AED 30.00",
        "link": "noon.com/uae-en/12-piece-porcelain-dinner-set-plates-dishes-bowls-serves-4-poppy/N30536383A/p/?o=c617aa64d07ca65f"
    },
    {
        "title": "noon east Ultra Sharp Blade Box Grater Green/White 32 x 11 x 11cm",
        "discount": "76% Off",
        "old_price": "AED 39",
        "new_price": "AED 9.00",
        "link": "noon.com/uae-en/ultra-sharp-blade-box-grater-green-white-32-x-11-x-11cm/N39861484A/p/?o=dbb41e8149c934df"
    },
    {
        "title": "noon east 15-Bar Espresso Coffee Making Machine 1.2 L 850 W CM-8500A-GS Dark Blue",
        "discount": "76% Off",
        "old_price": "AED 499",
        "new_price": "AED 119.00",
        "link": "noon.com/uae-en/15-bar-espresso-coffee-making-machine-1-2-l-850-w-cm-8500a-gs-dark-blue/N41576651A/p/?o=e361c2f957e8912a"
    },
    {
        "title": "noon east 18-Piece Porcelain Dinner Set, Plates, Dishes, Soup Plate, Serves 6 Dakota",
        "discount": "80% Off",
        "old_price": "AED 199",
        "new_price": "AED 39.00",
        "link": "noon.com/uae-en/18-piece-porcelain-dinner-set-plates-dishes-soup-plate-serves-6-dakota/N45309496A/p/?o=bda532da9424b83d"
    },
    {
        "title": "noon east 15-Bar Espresso Coffee Making Machine 1.2 L 850 W CM-8500A-GS Light Yellow",
        "discount": "76% Off",
        "old_price": "AED 499",
        "new_price": "AED 119.00",
        "link": "noon.com/uae-en/15-bar-espresso-coffee-making-machine-1-2-l-850-w-cm-8500a-gs-light-yellow/N41576656A/p/?o=fed6629b6958522c"
    },
    {
        "title": "KRYPTON Electric Kettle 1.8 L 1500 W KNK6062 Pink",
        "discount": "77% Off",
        "old_price": "AED 149",
        "new_price": "AED 34.00",
        "link": "noon.com/uae-en/electric-kettle-1-8-l-1500-w-knk6062-pink/N22638898A/p/?o=b94a0e8b992e85ce"
    },
    {
        "title": "noon east Classic 100% Cotton 200 Thread Count Fitted  Sheet And 1 Pillow Cover - Bed Sheet 120x200 + 25 cm + 1 Pillowcase 50x75 cm Janis Twin",
        "discount": "76% Off",
        "old_price": "AED 169",
        "new_price": "AED 39.00",
        "link": "noon.com/uae-en/classic-100-cotton-200-thread-count-fitted-sheet-and-1-pillow-cover-bed-sheet-120x200-25-cm-1-pillowcase-50x75-cm-janis-twin/N26469134A/p/?o=b697321e943a21cd"
    },
    {
        "title": "O General AC Remote Control AR-JW2 White/Grey/Yellow",
        "discount": "78% Off",
        "old_price": "AED 78",
        "new_price": "AED 17.00",
        "link": "noon.com/uae-en/ac-remote-control-ar-jw2-white-grey-yellow/N22670536A/p/?o=dd36ef93fa8e7f6a"
    },
    {
        "title": "Hometown Decorative Cotton Quality Area Rugs Multicolor 50X80cm",
        "discount": "76% Off",
        "old_price": "AED 63",
        "new_price": "AED 15.00",
        "link": "noon.com/uae-en/decorative-cotton-quality-area-rugs-multicolor-50x80cm/N46441651A/p/?o=c5d34bc8d7b7c76e"
    },
    {
        "title": "noon east 18-Piece Porcelain Dinner Set, Plates, Dishes, Bowls, Serves 6 Dandellion",
        "discount": "77% Off",
        "old_price": "AED 199",
        "new_price": "AED 45.00",
        "link": "noon.com/uae-en/18-piece-porcelain-dinner-set-plates-dishes-bowls-serves-6-dandellion/N30536405A/p/?o=a1f743127ff2245d"
    },
    {
        "title": "Deals for Less 6-Piece Bohemian Design Dining Chair Cover Set Beige/Blue",
        "discount": "75% Off",
        "old_price": "AED 199",
        "new_price": "AED 49.40",
        "link": "noon.com/uae-en/6-piece-bohemian-design-dining-chair-cover-set-beige-blue/N18950342A/p/?o=be3f5fb6aef961bb"
    },
    {
        "title": "noon east 16 Pc Set Stainless Steel Cutlery Silverware Flatware Sets, Knife, Fork, Spoon, Tea Spoon Melody Silver",
        "discount": "81% Off",
        "old_price": "AED 99",
        "new_price": "AED 18.00",
        "link": "noon.com/uae-en/16-pc-set-stainless-steel-cutlery-silverware-flatware-sets-knife-fork-spoon-tea-spoon-melody-silver/N47143712A/p/?o=c2093116c84ec02c"
    },
    {
        "title": "noon east 18-Piece Porcelain Dinner Set, Plates, Dishes, Soup Plate, Serves 6 Floral Meadow",
        "discount": "80% Off",
        "old_price": "AED 199",
        "new_price": "AED 39.00",
        "link": "noon.com/uae-en/18-piece-porcelain-dinner-set-plates-dishes-soup-plate-serves-6-floral-meadow/N45309501A/p/?o=eed5ef23cb1e6d2f"
    },
    {
        "title": "noon east 18-Piece Porcelain Dinner Set, Plates, Dishes, Bowls, Serves 6 Boho",
        "discount": "77% Off",
        "old_price": "AED 199",
        "new_price": "AED 45.00",
        "link": "noon.com/uae-en/18-piece-porcelain-dinner-set-plates-dishes-bowls-serves-6-boho/N30536402A/p/?o=d382a1edd005c3ba"
    },
    {
        "title": "Amal Stylish Nylon Kitchen Tools 6-Piece Pastel Multicolour",
        "discount": "76% Off",
        "old_price": "AED 39",
        "new_price": "AED 9.00",
        "link": "noon.com/uae-en/stylish-nylon-kitchen-tools-6-piece-pastel-multicolour/N42664749A/p/?o=dc21fb5cd9ed109c"
    },
    {
        "title": "Amal Silicone Ice Cube Mold Smile 2-Piece Light Blue/Brown Light Blue/Brown",
        "discount": "80% Off",
        "old_price": "AED 15",
        "new_price": "AED 3.00",
        "link": "noon.com/uae-en/silicone-ice-cube-mold-smile-2-piece-light-blue-brown-light-blue-brown/N39007164A/p/?o=d82caa96d8577cfd"
    },
    {
        "title": "noon east 18-Piece Porcelain Dinner Set, Plates, Dishes, Bowls, Serves 6 Marrakesh",
        "discount": "75% Off",
        "old_price": "AED 199",
        "new_price": "AED 49.00",
        "link": "noon.com/uae-en/18-piece-porcelain-dinner-set-plates-dishes-bowls-serves-6-marrakesh/N30536410A/p/?o=cf0171703a2b029e"
    },
    {
        "title": "kwb LED Solar String Lights Red/Green/Blue 7meter",
        "discount": "77% Off",
        "old_price": "AED 125",
        "new_price": "AED 28.50",
        "link": "noon.com/uae-en/led-solar-string-lights-red-green-blue-7meter/N13801708A/p/?o=d524b299b9bdc88d"
    },
    {
        "title": "Amal 144 Thread Count Home Essential Fitted Sheet Set/3 - 90X190+25cm, 2 Pillow Case 50X75 cm Cotton Garnet Red Single",
        "discount": "79% Off",
        "old_price": "AED 159",
        "new_price": "AED 32.00",
        "link": "noon.com/uae-en/144-thread-count-home-essential-fitted-sheet-set-3-90x190-25cm-2-pillow-case-50x75-cm-cotton-garnet-red-single/N43682780A/p/?o=fda31fd9349b43fe"
    },
    {
        "title": "TGGT Coffee Capsule Holder And Stand Black/Silver -centimeter",
        "discount": "77% Off",
        "old_price": "AED 204",
        "new_price": "AED 46.50",
        "link": "noon.com/uae-en/coffee-capsule-holder-and-stand-black-silver-centimeter/N15775219A/p/?o=a71e4cabf0454e0d"
    },
    {
        "title": "noon east 12-Piece Porcelain Dinner Set, Plates, Dishes, Bowls, Serves 4 Sprouts",
        "discount": "75% Off",
        "old_price": "AED 129",
        "new_price": "AED 32.00",
        "link": "noon.com/uae-en/12-piece-porcelain-dinner-set-plates-dishes-bowls-serves-4-sprouts/N30536386A/p/?o=a95303514b12e56b"
    },
    {
        "title": "Amal 4 Pc Table Spoon Stainless Steel Cutlery Flatware Sets Aster Silver",
        "discount": "82% Off",
        "old_price": "AED 29",
        "new_price": "AED 5.00",
        "link": "noon.com/uae-en/4-pc-table-spoon-stainless-steel-cutlery-flatware-sets-aster-silver/N43299823A/p/?o=e8ed53b70bd693fb"
    },
    {
        "title": "noon east Household Multi-Purpose Kitchen Shear For Cutting Meat, Poultry, Seafood, Vegetable Red/Black/Silver 7 x 3 x 24.5cm",
        "discount": "75% Off",
        "old_price": "AED 29",
        "new_price": "AED 7.00",
        "link": "noon.com/uae-en/household-multi-purpose-kitchen-shear-for-cutting-meat-poultry-seafood-vegetable-red-black-silver-7-x-3-x-24-5cm/N39861460A/p/?o=a04a05f7ef34b85b"
    },
    {
        "title": "noon east 16 Pc Set Reusable Portable Stainless Steel Cutlery Flatware Sets Spoon, Fork, Knife Silver Allegro",
        "discount": "81% Off",
        "old_price": "AED 99",
        "new_price": "AED 18.00",
        "link": "noon.com/uae-en/16-pc-set-reusable-portable-stainless-steel-cutlery-flatware-sets-spoon-fork-knife-silver-allegro/N47144982A/p/?o=c747b548a075a3db"
    },
    {
        "title": "DaDa Home Kitchen Utensils Removable Wall Sticker Brown 60x45cm",
        "discount": "75% Off",
        "old_price": "AED 39",
        "new_price": "AED 9.50",
        "link": "noon.com/uae-en/kitchen-utensils-removable-wall-sticker-brown-60x45cm/N12479308A/p/?o=e5106e07678e478a"
    },
    {
        "title": "Amal 144 Thread Count Home Essential Fitted Sheet Set/3 - 120X200+33cm, 2 Pillow Case 50X75 cm Cotton White Twin",
        "discount": "75% Off",
        "old_price": "AED 159",
        "new_price": "AED 39.00",
        "link": "noon.com/uae-en/144-thread-count-home-essential-fitted-sheet-set-3-120x200-33cm-2-pillow-case-50x75-cm-cotton-white-twin/N43682821A/p/?o=c31b3fd7f445d83f"
    },
    {
        "title": "chicago metallic Maryann Cake Pan Black 27x6centimeter",
        "discount": "76% Off",
        "old_price": "AED 100",
        "new_price": "AED 23.75",
        "link": "noon.com/uae-en/maryann-cake-pan-black-27x6centimeter/N17942578A/p/?o=c203d9f2f90df0ea"
    },
    {
        "title": "noon east 18-Piece Porcelain Dinner Set, Plates, Dishes, Bowls, Serves 6 Portia",
        "discount": "75% Off",
        "old_price": "AED 199",
        "new_price": "AED 49.00",
        "link": "noon.com/uae-en/18-piece-porcelain-dinner-set-plates-dishes-bowls-serves-6-portia/N39407388A/p/?o=dcaf98486024618b"
    },
    {
        "title": "Royal Polar Ice Cube Tray Black 5inch",
        "discount": "79% Off",
        "old_price": "AED 99",
        "new_price": "AED 20.00",
        "link": "noon.com/uae-en/ice-cube-tray-black-5inch/N35147026A/p/?o=caff453a34007e8a"
    },
    {
        "title": "Mother Comfort U Shaped Comfortable Maternity Pillow Made With Microfiber - White Microfiber White 70x25x120cm",
        "discount": "76% Off",
        "old_price": "AED 220",
        "new_price": "AED 52.00",
        "link": "noon.com/uae-en/u-shaped-comfortable-maternity-pillow-made-with-microfiber-white-microfiber-white-70x25x120cm/N16197172A/p/?o=bc43099e97197ada"
    },
    {
        "title": "Everrich 6-Piece Stretchable Tear Resistant Silicone Lids Multicolour 155g",
        "discount": "76% Off",
        "old_price": "AED 33",
        "new_price": "AED 7.70",
        "link": "noon.com/uae-en/6-piece-stretchable-tear-resistant-silicone-lids-multicolour-155g/N16565683A/p/?o=dd91a277a8ee418b"
    },
    {
        "title": "Toshionics LCD Projection Voice Talking Digital Alarm Clock Black 10x8x8cm",
        "discount": "78% Off",
        "old_price": "AED 99",
        "new_price": "AED 20.95",
        "link": "noon.com/uae-en/lcd-projection-voice-talking-digital-alarm-clock-black-10x8x8cm/N46205187A/p/?o=fd1cbd2c8c3bf7bb"
    },
    {
        "title": "XiuWoo 16 Colors Portable Modern Style Antique Designed Sunset Projection Light Lamp Multicolour 27 x 10 x 10cm",
        "discount": "76% Off",
        "old_price": "AED 150",
        "new_price": "AED 36.00",
        "link": "noon.com/uae-en/16-colors-portable-modern-style-antique-designed-sunset-projection-light-lamp-multicolour-27-x-10-x-10cm/N48113266A/p/?o=c4d11e978ca76eaf"
    },
    {
        "title": "Silentnight 2-Piece Duck Feather Pillow Foam White 75 x 50centimeter",
        "discount": "76% Off",
        "old_price": "AED 470",
        "new_price": "AED 110.00",
        "link": "noon.com/uae-en/2-piece-duck-feather-pillow-foam-white-75-x-50centimeter/N13069350A/p/?o=d44719dfc3b434bc"
    },
    {
        "title": "SKYROKU Digital Food Scale Silver",
        "discount": "76% Off",
        "old_price": "AED 99",
        "new_price": "AED 23.75",
        "link": "noon.com/uae-en/digital-food-scale-silver/N23620531A/p/?o=cdeb4c25dad9117e"
    }
]